smartcall.py
smartcall-0.1.0.dist-info/WHEEL
smartcall-0.1.0.dist-info/METADATA
smartcall-0.1.0.dist-info/RECORD
