Metadata-Version: 2.3
Name: smartcall
Version: 0.1.0
Summary: Call a function, and pass it only the arguments it expects.
Author-email: Kale Kundert <kale@thekunderts.net>
Requires-Python: ~=3.10
Classifier: Programming Language :: Python :: 3
Requires-Dist: sphinx ; extra == "doc"
Requires-Dist: sphinx_rtd_theme ; extra == "doc"
Requires-Dist: myst_parser ; extra == "doc"
Requires-Dist: pytest ; extra == "test"
Requires-Dist: parametrize_from_file ; extra == "test"
Project-URL: Bug Tracker, https://github.com/kalekundert/smartcall/issues
Project-URL: Continuous Integration, https://github.com/kalekundert/smartcall/actions
Project-URL: Documentation, https://smartcall.readthedocs.io/en/latest/
Project-URL: Test Coverage, https://app.codecov.io/github/kalekundert/smartcall
Project-URL: Version Control, https://github.com/kalekundert/smartcall
Provides-Extra: doc
Provides-Extra: test
